{
  "node_modules/@sveltejs/kit/src/runtime/client/start.js": {
    "file": "_app/immutable/start-209b57d4.js",
    "src": "node_modules/@sveltejs/kit/src/runtime/client/start.js",
    "isEntry": true,
    "imports": [
      "_preload-helper-aa6bc0ce.js",
      "_index-d8564362.js",
      "_singletons-4343154a.js",
      "_paths-6cd3a76e.js"
    ],
    "dynamicImports": [
      ".svelte-kit/generated/nodes/0.js",
      ".svelte-kit/generated/nodes/1.js",
      ".svelte-kit/generated/nodes/2.js",
      ".svelte-kit/generated/nodes/3.js",
      ".svelte-kit/generated/nodes/4.js",
      ".svelte-kit/generated/nodes/5.js"
    ]
  },
  "src/routes/+layout.svelte": {
    "file": "_app/immutable/components/pages/_layout.svelte-d252bbec.js",
    "src": "src/routes/+layout.svelte",
    "isEntry": true,
    "imports": [
      "_index-d8564362.js",
      "_paths-6cd3a76e.js",
      "_misc-6efa9b16.js"
    ],
    "css": [
      "_app/immutable/assets/_layout-f4ce4a63.css"
    ]
  },
  "src/routes/+error.svelte": {
    "file": "_app/immutable/components/pages/_error.svelte-ab2a5539.js",
    "src": "src/routes/+error.svelte",
    "isEntry": true,
    "imports": [
      "_index-d8564362.js",
      "_singletons-4343154a.js"
    ]
  },
  "src/routes/+page.svelte": {
    "file": "_app/immutable/components/pages/_page.svelte-ec00ba62.js",
    "src": "src/routes/+page.svelte",
    "isEntry": true,
    "imports": [
      "_index-d8564362.js",
      "_paths-6cd3a76e.js",
      "_misc-6efa9b16.js",
      "_transform-d9c6ebaf.js",
      "_descending-97f17103.js",
      "_Icon-6ba03468.js",
      "_preload-helper-aa6bc0ce.js",
      "_index-cce15019.js"
    ],
    "dynamicImports": [
      "node_modules/vanilla-colorful/hex-color-picker.js"
    ],
    "css": [
      "_app/immutable/assets/_page-aaa9eadd.css"
    ]
  },
  "src/routes/demo/elements/+page.svelte": {
    "file": "_app/immutable/components/pages/demo/elements/_page.svelte-52fa4bb9.js",
    "src": "src/routes/demo/elements/+page.svelte",
    "isEntry": true,
    "imports": [
      "_index-d8564362.js"
    ],
    "css": [
      "_app/immutable/assets/_page-83b17d31.css"
    ]
  },
  "src/routes/demo/fonts/+page.svelte": {
    "file": "_app/immutable/components/pages/demo/fonts/_page.svelte-40814f20.js",
    "src": "src/routes/demo/fonts/+page.svelte",
    "isEntry": true,
    "imports": [
      "_index-d8564362.js",
      "_transform-d9c6ebaf.js",
      "_paths-6cd3a76e.js",
      "_descending-97f17103.js"
    ],
    "css": [
      "_app/immutable/assets/_page-694798f8.css"
    ]
  },
  "src/routes/wheel/+page.svelte": {
    "file": "_app/immutable/components/pages/wheel/_page.svelte-ae2765e1.js",
    "src": "src/routes/wheel/+page.svelte",
    "isEntry": true,
    "imports": [
      "_index-d8564362.js",
      "_paths-6cd3a76e.js",
      "_transform-d9c6ebaf.js",
      "_Icon-6ba03468.js"
    ],
    "css": [
      "_app/immutable/assets/_page-f7ca95eb.css"
    ]
  },
  "src/routes/+layout.js": {
    "file": "_app/immutable/modules/pages/_layout.js-7b9cbfbc.js",
    "src": "src/routes/+layout.js",
    "isEntry": true,
    "imports": [
      "__layout-8d2a742b.js"
    ]
  },
  "_singletons-4343154a.js": {
    "file": "_app/immutable/chunks/singletons-4343154a.js",
    "imports": [
      "_index-cce15019.js",
      "_paths-6cd3a76e.js"
    ]
  },
  "_paths-6cd3a76e.js": {
    "file": "_app/immutable/chunks/paths-6cd3a76e.js"
  },
  "_preload-helper-aa6bc0ce.js": {
    "file": "_app/immutable/chunks/preload-helper-aa6bc0ce.js"
  },
  "_index-d8564362.js": {
    "file": "_app/immutable/chunks/index-d8564362.js"
  },
  "_index-cce15019.js": {
    "file": "_app/immutable/chunks/index-cce15019.js",
    "imports": [
      "_index-d8564362.js"
    ]
  },
  "_misc-6efa9b16.js": {
    "file": "_app/immutable/chunks/misc-6efa9b16.js",
    "imports": [
      "_index-cce15019.js"
    ]
  },
  "__layout-8d2a742b.js": {
    "file": "_app/immutable/chunks/_layout-8d2a742b.js"
  },
  "_transform-d9c6ebaf.js": {
    "file": "_app/immutable/chunks/transform-d9c6ebaf.js"
  },
  "_Icon-6ba03468.js": {
    "file": "_app/immutable/chunks/Icon-6ba03468.js",
    "imports": [
      "_index-d8564362.js",
      "_paths-6cd3a76e.js",
      "_transform-d9c6ebaf.js"
    ],
    "css": [
      "_app/immutable/assets/Icon-ea8f1350.css"
    ]
  },
  "_descending-97f17103.js": {
    "file": "_app/immutable/chunks/descending-97f17103.js"
  },
  ".svelte-kit/generated/nodes/0.js": {
    "file": "_app/immutable/chunks/0-a364f3ff.js",
    "src": ".svelte-kit/generated/nodes/0.js",
    "isDynamicEntry": true,
    "imports": [
      "__layout-8d2a742b.js",
      "src/routes/+layout.svelte"
    ]
  },
  ".svelte-kit/generated/nodes/1.js": {
    "file": "_app/immutable/chunks/1-99b10d44.js",
    "src": ".svelte-kit/generated/nodes/1.js",
    "isDynamicEntry": true,
    "imports": [
      "src/routes/+error.svelte"
    ]
  },
  ".svelte-kit/generated/nodes/2.js": {
    "file": "_app/immutable/chunks/2-de5d9f02.js",
    "src": ".svelte-kit/generated/nodes/2.js",
    "isDynamicEntry": true,
    "imports": [
      "src/routes/+page.svelte"
    ]
  },
  ".svelte-kit/generated/nodes/3.js": {
    "file": "_app/immutable/chunks/3-db19a9fd.js",
    "src": ".svelte-kit/generated/nodes/3.js",
    "isDynamicEntry": true,
    "imports": [
      "src/routes/demo/elements/+page.svelte"
    ]
  },
  ".svelte-kit/generated/nodes/4.js": {
    "file": "_app/immutable/chunks/4-48379120.js",
    "src": ".svelte-kit/generated/nodes/4.js",
    "isDynamicEntry": true,
    "imports": [
      "src/routes/demo/fonts/+page.svelte"
    ]
  },
  ".svelte-kit/generated/nodes/5.js": {
    "file": "_app/immutable/chunks/5-3f525dfd.js",
    "src": ".svelte-kit/generated/nodes/5.js",
    "isDynamicEntry": true,
    "imports": [
      "src/routes/wheel/+page.svelte"
    ]
  },
  "node_modules/vanilla-colorful/hex-color-picker.js": {
    "file": "_app/immutable/chunks/hex-color-picker-5c6f56b9.js",
    "src": "node_modules/vanilla-colorful/hex-color-picker.js",
    "isDynamicEntry": true
  },
  "src/routes/wheel/+page.css": {
    "file": "_app/immutable/assets/_page-f7ca95eb.css",
    "src": "src/routes/wheel/+page.css"
  },
  "Icon.css": {
    "file": "_app/immutable/assets/Icon-ea8f1350.css",
    "src": "Icon.css"
  },
  "src/routes/demo/elements/+page.css": {
    "file": "_app/immutable/assets/_page-83b17d31.css",
    "src": "src/routes/demo/elements/+page.css"
  },
  "src/routes/+page.css": {
    "file": "_app/immutable/assets/_page-aaa9eadd.css",
    "src": "src/routes/+page.css"
  },
  "src/routes/demo/fonts/+page.css": {
    "file": "_app/immutable/assets/_page-694798f8.css",
    "src": "src/routes/demo/fonts/+page.css"
  },
  "src/routes/+layout.css": {
    "file": "_app/immutable/assets/_layout-f4ce4a63.css",
    "src": "src/routes/+layout.css"
  }
}